sumer/Timer.py
sumer/YearMonth.py
sumer/YearQuarter.py
sumer/__init__.py
sumer/add_time.py
sumer/elapsed_time.py
sumer/get_month.py
sumer/get_time.py
sumer/remove_non_alphanumeric.py
sumer/to_date_part.py
sumer/to_quarter.py
sumer/numbers/FlexibleNumber.py
sumer/numbers/NumberPart.py
sumer/numbers/__init__.py
sumer-1.1.dist-info/LICENSE
sumer-1.1.dist-info/METADATA
sumer-1.1.dist-info/WHEEL
sumer-1.1.dist-info/top_level.txt
sumer-1.1.dist-info/RECORD
