Metadata-Version: 2.1
Name: sumer
Version: 1.1
Summary: Sumer is a Python library for dealing with time (and date).
Home-page: https://github.com/idin/sumer
Author: Idin
Author-email: py@idin.ca
License: MIT
Platform: UNKNOWN
Requires-Python: ~=3.6
